Workbook

Sheet Main
A1: Date | T1: * | BK1: * | CT1: * | EC1: * | FL1: * | IB1: * | IT1: * | KO1: * | ZY1: * | API1: * | APO1: *
A2: 43934 | C2: TRADE DETAILS | T2: * | AE2: FINAL SPECIFICATIONS TO ViU ADJUSTMENT | BD2: RESULT OF ViU ADJUSTMENT | BK2: * | BM2: WORKINGS FOR ViU ADJUSTMNET OF TRADE BAUXITE | CT2: * | CV2: WORKINGS FOR ViU ADJUSTMNET OF SPECIFIC INDEX | EC2: * | EE2: WORKINGS FOR ViU ADJUSTMNET OF GENERAL INDEX | FL2: * | FN2: WORKINGS FOR ViU ADJUSTMNET OF OLD CBIX INDEX | IB2: * | ID2: NOMINAL MINE / INDEX SPECIFATIONS | IT2: * | IV2: COMMON DATA INPUTS | KO2: * | KQ2: FREIGHT CALCULATIONS TO ACTUAL NOMINATED PORT | ZY2: * | AAA2: FREIGHT CALCULATIONS TO QINGDAO (THE REFERENCE PORT USED FOR ALL THE INDEX CALCULATIONS) | API2: * | APK2: FINAL FREIGHT VALUES | APO2: * | APQ2: THE END
T3: * | AQ3: {=IF(AO10="no",0,INDEX('Indices Mines Exporting Ports'!$E$3:$E$10,MATCH(2,1/(('Indices Mines Exporting Ports'!$B$3:$B$10<=Main!$C10)*('Indices Mines Exporting Ports'!$D$3:$D$10=Main!$AP10)))))} -> 0 | BK3: * | CT3: * | EC3: * | FL3: * | IB3: * | IT3: * | KO3: * | SG3: Leg 2 | ZY3: * | API3: * | APO3: *
T4: * | BK4: * | CT4: * | EC4: * | FL4: * | IB4: * | IT4: * | KO4: * | ZY4: * | API4: * | APO4: *
C5: Trade Details Reported to CM (don't change any of the reported details here … make changes in the "Final Specification" section) …* Data is essential - other fields can be left blank | T5: * | V5: Using Modifing equations for Mine Spec (to account for missing values in raw data) | AE5: Final Specification used for trade (hard code any values changed from suggested and green fill these cells) | BK5: * | BM5: Bauxite at hand cost to alumina | CT5: * | CV5: Specific Index ViU calculation | EC5: * | EE5: General Index ViU calculation | FL5: * | FN5: for Old CBIX - Bauxite at hand cost to alumina | GU5: Old CBIX calculation | IB5: * | ID5: Nominal Mines Data (do not alter any information in this section - do this in the "Final Specifications" section) | IT5: * | IV5: China input prices | JA5: FX rates | JF5: Global Factors | KO5: * | KQ5: Freight calcualtions - Actual port - first leg | ND5: Fuel Prices | SH5: Freight calcualtions - Actual port - second leg | UU5: Fuel Prices | ZY5: * | AAA5: Freight calcualtions - Qingdao - first leg | ACN5: Fuel Prices | AHR5: Freight calcualtions - Qingdao - second leg | AKE5: Fuel Prices | API5: * | APK5: Qingdao Freight | APL5: Actual Port Freight | APM5: Freight Differential | APO5: *
T6: * | BK6: * | BM6: Bauxite Details - input | BX6: China processing factors | CG6: Alumina production cost calculations - excluding common elements | CT6: * | CV6: Index Bauxite Details | DG6: China processing factors | DP6: Alumina production cost calculations - excluding common elements | EC6: * | EE6: Index Bauxite Details | EP6: China processing factors | EY6: Alumina production cost calculations - excluding common elements | FL6: * | FN6: Bauxite Details - input | FY6: China processing factors | GH6: Alumina production cost calculations - excluding common elements | GU6: Index Bauxite Details | HF6: China processing factors | HO6: Alumina production cost calculations - excluding common elements | IB6: * | IT6: * | KO6: * | KX6: Exporting Port Details - Loading rate | LF6: Port Linakges | NJ6: Importing Port Details | OH6: Canals details | PY6: Canals costs workings | QT6: Final costing up for Leg | SO6: Exporting Port Details - Loading rate | SW6: Port Linakges | VA6: Importing Port Details | VY6: Canals details | XP6: Canals costs workings | YK6: Final costing up for Leg | ZY6: * | AAH6: Exporting Port Details - Loading rate | AAP6: Port Linakges | ACT6: Importing Port Details | ADR6: Canals details | AFI6: Canals costs workings | AGD6: Final costing up for Leg | AHY6: Exporting Port Details - Loading rate | AIG6: Port Linakges | AKK6: Importing Port Details | ALI6: Canals details | AMZ6: Canals costs workings | ANU6: Final costing up for Leg | API6: * | APO6: *
T7: * | AN7: Changed | BD7: Guinea 45/3 LT | BE7: Indonesian LT | BF7: Australia HT | BG7: CBIX LT | BH7: CBIX HT | BI7: CBIX OLD | BK7: * | CT7: * | EC7: * | FL7: * | IB7: * | IT7: * | IZ7: used n lookup => | JA7: RMB | JB7: AUD | JC7: USD | JD7: SDR | KO7: * | LF7: VLOC | LM7: Capesize | LT7: Suezmax | MA7: NeoPanamax | MH7: Panamax | MO7: Supramax | MV7: Handysize | NC7: used n lookup => | ND7: HSFO | NE7: VLSFO | NF7: LNG | NG7: MGO_Regular | NH7: MGO_Low_Sulph | SW7: VLOC | TD7: Capesize | TK7: Suezmax | TR7: NeoPanamax | TY7: Panamax | UF7: Supramax | UM7: Handysize | UT7: used n lookup => | UU7: HSFO | UV7: VLSFO | UW7: LNG | UX7: MGO_Regular | UY7: MGO_Low_Sulph | VY7: 2 | VZ7: 3 | WA7: 4 | WB7: 5 | WC7: 6 | WD7: 7 | WE7: 8 | WF7: 9 | WG7: 10 | WH7: 11 | WI7: 12 | WJ7: 13 | WK7: 14 | WL7: 15 | WM7: 16 | WN7: 17 | WO7: 18 | WP7: 19 | WQ7: 20 | WR7: 21 | WS7: 22 | WT7: 23 | WU7: 24 | WV7: 25 | WW7: 26 | WX7: 27 | WY7: 28 | WZ7: 29 | XA7: 30 | XB7: 31 | XC7: 32 | XD7: 33 | XE7: 34 | XF7: 35 | XG7: 36 | XH7: 37 | XI7: 38 | XJ7: 39 | XK7: 40 | XL7: 41 | XM7: 42 | XN7: 43 | XP7: 1 | XQ7: 2 | XR7: 3 | XS7: 4 | XT7: 5 | XU7: 6 | XV7: 7 | XW7: 8 | XX7: 9 | XY7: 10 | XZ7: 11 | YA7: 12 | YB7: 13 | YC7: 14 | YD7: 15 | YE7: 16 | YF7: 17 | YG7: 18 | YH7: 19 | YI7: 20 | ZY7: * | AAP7: VLOC | AAW7: Capesize | ABD7: Suezmax | ABK7: NeoPanamax | ABR7: Panamax | ABY7: Supramax | ACF7: Handysize | ACM7: used n lookup => | ACN7: HSFO | ACO7: VLSFO | ACP7: LNG | ACQ7: MGO_Regular | ACR7: MGO_Low_Sulph | AIG7: VLOC | AIN7: Capesize | AIU7: Suezmax | AJB7: NeoPanamax | AJI7: Panamax | AJP7: Supramax | AJW7: Handysize | AKD7: used n lookup => | AKE7: HSFO | AKF7: VLSFO | AKG7: LNG | AKH7: MGO_Regular | AKI7: MGO_Low_Sulph | ALI7: 2 | ALJ7: 3 | ALK7: 4 | ALL7: 5 | ALM7: 6 | ALN7: 7 | ALO7: 8 | ALP7: 9 | ALQ7: 10 | ALR7: 11 | ALS7: 12 | ALT7: 13 | ALU7: 14 | ALV7: 15 | ALW7: 16 | ALX7: 17 | ALY7: 18 | ALZ7: 19 | AMA7: 20 | AMB7: 21 | AMC7: 22 | AMD7: 23 | AME7: 24 | AMF7: 25 | AMG7: 26 | AMH7: 27 | AMI7: 28 | AMJ7: 29 | AMK7: 30 | AML7: 31 | AMM7: 32 | AMN7: 33 | AMO7: 34 | AMP7: 35 | AMQ7: 36 | AMR7: 37 | AMS7: 38 | AMT7: 39 | AMU7: 40 | AMV7: 41 | AMW7: 42 | AMX7: 43 | AMZ7: 1 | ANA7: 2 | ANB7: 3 | ANC7: 4 | AND7: 5 | ANE7: 6 | ANF7: 7 | ANG7: 8 | ANH7: 9 | ANI7: 10 | ANJ7: 11 | ANK7: 12 | ANL7: 13 | ANM7: 14 | ANN7: 15 | ANO7: 16 | ANP7: 17 | ANQ7: 18 | ANR7: 19 | ANS7: 20 | API7: * | APO7: *
C8: Date* | D8: CM Data Source | E8: Mine* (don't worry if mine appears twice - just pick correct name) | F8: Price* | G8: Price Type* | H8: Price Basis* | I8: Total Alumina | J8: LT Avail. Alumina | K8: Total Silica | L8: LT R.Silica | M8: Quartz / HT Silica | N8: Mono-hydrate / HT Extble Alumina | O8: Moisture | P8: Tonnage (leave blank to invoke default) | Q8: Exporting Port (must be the physical port where first loaded) (leave blank to invoke default) | R8: Importing Port (must be the physical port where unloaded) (leave blank to invoke default) (don't worry if port appears twice - just pick correct name) | T8: * | V8: Mine | W8: Total Alumina | X8: LT Avail. Alumina | Y8: Total Silica | Z8: LT R.Silica | AA8: Quartz / HT Silica | AB8: Mono-hydrate / HT Alumina | AC8: Moisture | AE8: Mine | AF8: Total Alumina | AG8: LT Avail. Alumina | AH8: Total Silica | AI8: LT R.Silica | AJ8: Quartz / HT Silica | AK8: Mono-hydrate / HT Extble Alumina | AL8: Moisture | AM8: Processing | AN8: Cargo Tonnage | AO8: Double Leg Shipping? (South America special transload leg) | AP8: Exporting Port | AQ8: South America special transloading Port | AR8: South america special transloading cargo tonnage | AS8: Importing Port | AT8: Specific Index | AU8: General Index | AV8: Price Type | AW8: Price Basis | AX8: Price FOB | AY8: Freight (adjusted to Qingdao) | AZ8: Price CIF (Port adjustyed to Qingdao) | BA8: Processing Penalties to be applied (for organics, goehtite, impurities, crushing etc) | BB8: EXPLANITORY NOTES RECORD (on changes made to final spec etc) | BC8: Old CBIX type Calc | BD8: INDEX VALUE Guinea 45/3 LT | BE8: INDEX VALUE Indonesian LT | BF8: INDEX VALUE Australia HT | BG8: CBIX LT | BH8: CBIX HT | BI8: Old CBIX | BK8: * | BM8: Price | BN8: Total Alumina | BO8: LT Avail. Alumina | BP8: Total Silica | BQ8: LT R.Silica | BR8: Quartz / HT Silica | BS8: Mono-hydrate / HT Alumina | BT8: Moisture | BU8: Processing | BV8: Processing Penalties | BX8: HT Alumina Dissolution | BY8: DSP Al2O3:SiO2 (wt/wt) | BZ8: DSP NaOH:SiO2 (wt/wt) | CA8: Lime rate (wt/wt_AA) | CB8: Lig Coal (GJ/t) | CC8: Quartz Attack | CD8: Extraction Efficiency % | CE8: Caustic wash loss (t.NaOH/t.aa) | CG8: Reactive Alumina | CH8: Reactive Silica | CI8: Available Alumina | CJ8: Tonnes per Tonne | CK8: Bauxite Cost Incl. Processing Penalties | CL8: Caustic Use t.NAOH / t.AA | CM8: Caustic cost | CN8: Thermal Energy Cost | CO8: Lime Cost | CP8: Mud make | CQ8: Mud Disposal Cost | CR8: Total Cost | CT8: * | CV8: Calculated Index Price Equivalent | CW8: Total Alumina | CX8: LT Avail. Alumina | CY8: Total Silica | CZ8: LT R.Silica | DA8: Quartz / HT Silica | DB8: Mono-hydrate / HT Alumina | DC8: Moisture | DD8: Processing | DE8: Processing Penalties | DG8: HT Alumina Dissolution | DH8: DSP Al2O3:SiO2 (wt/wt) | DI8: DSP NaOH:SiO2 (wt/wt) | DJ8: Lime rate (wt/wt_AA) | DK8: Lig Coal (GJ/t) | DL8: Quartz Attack | DM8: Extraction Efficiency % | DN8: Caustic wash loss (t.NaOH/t.aa) | DP8: Reactive Alumina | DQ8: Reactive Silica | DR8: Available Alumina | DS8: Tonnes per Tonne | DT8: Bauxite Cost Incl. Processing Penalties | DU8: Caustic Use t.NAOH / t.AA | DV8: Caustic cost | DW8: Thermal Energy Cost | DX8: Lime Cost | DY8: Mud make | DZ8: Mud Disposal Cost | EA8: Total Cost | EC8: * | EE8: Calculated Index Price Equivalent | EF8: Total Alumina | EG8: LT Avail. Alumina | EH8: Total Silica | EI8: LT R.Silica | EJ8: Quartz / HT Silica | EK8: Mono-hydrate / HT Alumina | EL8: Moisture | EM8: Processing | EN8: Processing Penalties | EP8: HT Alumina Dissolution | EQ8: DSP Al2O3:SiO2 (wt/wt) | ER8: DSP NaOH:SiO2 (wt/wt) | ES8: Lime rate (wt/wt_AA) | ET8: Lig Coal (GJ/t) | EU8: Quartz Attack | EV8: Extraction Efficiency % | EW8: Caustic wash loss (t.NaOH/t.aa) | EY8: Reactive Alumina | EZ8: Reactive Silica | FA8: Available Alumina | FB8: Tonnes per Tonne | FC8: Bauxite Cost Incl. Processing Penalties | FD8: Caustic Use t.NAOH / t.AA | FE8: Caustic cost | FF8: Thermal Energy Cost | FG8: Lime Cost | FH8: Mud make | FI8: Mud Disposal Cost | FJ8: Total Cost | FL8: * | FN8: Price | FO8: Total Alumina | FP8: LT Avail. Alumina | FQ8: Total Silica | FR8: LT R.Silica | FS8: Quartz / HT Silica | FT8: Mono-hydrate / HT Alumina | FU8: Moisture | FV8: Processing | FW8: Processing Penalties | FY8: HT Alumina Dissolution | FZ8: DSP Al2O3:SiO2 (wt/wt) | GA8: DSP NaOH:SiO2 (wt/wt) | GB8: Lime rate (wt/wt_AA) | GC8: Lig Coal (GJ/t) | GD8: Quartz Attack | GE8: Extraction Efficiency % | GF8: Caustic wash loss (t.NaOH/t.aa) | GH8: Reactive Alumina | GI8: Reactive Silica | GJ8: Available Alumina | GK8: Tonnes per Tonne | GL8: Bauxite Cost Incl. Processing Penalties | GM8: Caustic Use t.NAOH / t.AA | GN8: Caustic cost | GO8: Thermal Energy Cost | GP8: Lime Cost | GQ8: Mud make | GR8: Mud Disposal Cost | GS8: Total Cost | GU8: Calculated Index Price Equivalent | GV8: Total Alumina | GW8: LT Avail. Alumina | GX8: Total Silica | GY8: LT R.Silica | GZ8: Quartz / HT Silica | HA8: Mono-hydrate / HT Alumina | HB8: Moisture | HC8: Processing | HD8: Processing Penalties | HF8: HT Alumina Dissolution | HG8: DSP Al2O3:SiO2 (wt/wt) | HH8: DSP NaOH:SiO2 (wt/wt) | HI8: Lime rate (wt/wt_AA) | HJ8: Lig Coal (GJ/t) | HK8: Quartz Attack | HL8: Extraction Efficiency % | HM8: Caustic wash loss (t.NaOH/t.aa) | HO8: Reactive Alumina | HP8: Reactive Silica | HQ8: Available Alumina | HR8: Tonnes per Tonne | HS8: Bauxite Cost Incl. Processing Penalties | HT8: Caustic Use t.NAOH / t.AA | HU8: Caustic cost | HV8: Thermal Energy Cost | HW8: Lime Cost | HX8: Mud make | HY8: Mud Disposal Cost | HZ8: Total Cost | IB8: * | ID8: Mine | IE8: Date | IF8: Total Alumina | IG8: LT Avail. Alumina | IH8: Total Silica | II8: LT R.Silica | IJ8: Quartz / HT Silica | IK8: Mono-hydrate / HT Alumina | IL8: Moisture | IM8: Processing | IN8: Processing Penalties to be applied | IO8: Tonnage typical vessel | IP8: Exporting Port | IQ8: Specific Index | IR8: General Index | IT8: * | IV8: Energy Price | IW8: Caustic Price | IX8: Lime Price | IY8: Mud Disposal Cost | JA8: RMB per US$ | JB8: AU$ per US$ | JC8: US$ per US$ | JD8: IMF Special Drawing Rights to US Dollar (SDR or XDR) per US$ | JF8: kcal per GJ | JG8: conversion kt to t | JH8: hours per day | JI8: legs per round trip | JJ8: shipping profit rate | JK8: Alumina mol weight | JL8: Silica Mol Wt | JM8: Kaolinite (Al2O3.2SiO2.2H20) - Al2O3:SiO2 ratio | JN8: Max % of vessel deadweight allowed for loading | JO8: LOA estimate correlation multiplier | JP8: LOA estimate correlation constant | JQ8: NRT estimate correlation multiplier | JR8: NRT estimate correlation constant | JS8: GRT estimate correlation multiplier | JT8: GRT estimate correlation constant | JU8: Minimum Lay days allowed | JV8: Minimum Lay days allowed as % of sailing time | JW8: Lay allowance Loading port | JX8: Extra time tie up + untie at each port | JY8: MDO/MGO burn vessel DWT denominator | JZ8: MDO/MGO burn vessel DWT slope | KA8: MDO/MGO burn vessel DWT constant | KB8: MDO/MGO burn vessel DWT ^2 coefficient | KC8: Main engine burn vessel DWT denominator | KD8: Main engine burn vessel DWT exponent | KE8: Main engine burn vessel DWT base constant | KF8: Main engine burn vessel DWT base slope | KG8: Main engine burn speed linear coefficient | KH8: Main engine burn speed ^2 coefficient | KI8: Main engine burn speed ^3 coefficient | KJ8: Main engine burn overall correction factor | KK8: Reference Port | KL8: Freight Insurance Rate | KM8: Freight Commission | KO8: * | KQ8: Vessel dwt | KR8: Vessel Class for timecharter & fuel burn rates | KS8: Vessel Class for distance, canals, loading and unloading rates, fuel prices | KT8: Estimated LOA (length over all) (m) | KU8: Estimated NRT (net register tons) | KV8: Estimated GRT (gross register tons) | KX8: Handysize | KY8: Supramax loading rates | KZ8: Panamax loading rates | LA8: NeoPanamax loading rate | LB8: Suezmax loading rate | LC8: Capesize loading rates | LD8: VLOC loading rates | LF8: Distance using Main Engine Fuel | LG8: Distance using Auxiliary Fuel | LH8: Applicable Time Charter Index | LI8: Applicable Fuel Region | LJ8: Main Engine Fuel | LK8: Auxiliary Fuel | LL8: Canals used | LM8: Distance using Main Engine Fuel | LN8: Distance using Auxiliary Fuel | LO8: Applicable Time Charter Index | LP8: Applicable Fuel Region | LQ8: Main Engine Fuel | LR8: Auxiliary Fuel | LS8: Canals used | LT8: Distance using Main Engine Fuel | LU8: Distance using Auxiliary Fuel | LV8: Applicable Time Charter Index | LW8: Applicable Fuel Region | LX8: Main Engine Fuel | LY8: Auxiliary Fuel | LZ8: Canals used | MA8: Distance using Main Engine Fuel | MB8: Distance using Auxiliary Fuel | MC8: Applicable Time Charter Index | MD8: Applicable Fuel Region | ME8: Main Engine Fuel | MF8: Auxiliary Fuel | MG8: Canals used | MH8: Distance using Main Engine Fuel | MI8: Distance using Auxiliary Fuel | MJ8: Applicable Time Charter Index | MK8: Applicable Fuel Region | ML8: Main Engine Fuel | MM8: Auxiliary Fuel | MN8: Canals used | MO8: Distance using Main Engine Fuel | MP8: Distance using Auxiliary Fuel | MQ8: Applicable Time Charter Index | MR8: Applicable Fuel Region | MS8: Main Engine Fuel | MT8: Auxiliary Fuel | MU8: Canals used | MV8: Distance using Main Engine Fuel | MW8: Distance using Auxiliary Fuel | MX8: Applicable Time Charter Index | MY8: Applicable Fuel Region | MZ8: Main Engine Fuel | NA8: Auxiliary Fuel | NB8: Canals used | ND8: HSFO (180 / 380) | NE8: VLSFO | NF8: LNG | NG8: MDO/MGO Regular | NH8: MDO/MGO Low Sulphur | NJ8: Unloading rate Handysize | NK8: Unloading rate Supramax | NL8: Unloading rate Panamax | NM8: Unloading rate NeoPanamax | NN8: Unloading rate Suezmax | NO8: Unloading rate Capesize | NP8: Unloading rate VLOC | NQ8: Currency | NR8: Fixed fee | NS8: RMB per day berthed | NT8: RMB per day anchored | NU8: RMB/T_Cargo (wet) | NV8: RMB/T_Cargo (wet)/day berthed | NW8: RMB/T_Cargo (wet)/day anchored | NX8: RMB/NRT | NY8: RMB/NRT/day berthed | NZ8: RMB/NRT/day anchored | OA8: RMB/GRT | OB8: RMB/GRT/day berthed | OC8: RMB/GRT/day anchored | OD8: RMB/LOA | OE8: RMB/LOA/day berthed | OF8: RMB/LOA/day anchored | OH8: Canal | OI8: Currency | OJ8: Capacity Tarrif Graduations (avg of laden and ballast) (tonnes per Tonnage Reference) (1,000,000 used at end as catch all) | OT8: Capacity Tarrifs (avg of laden and ballast) ("Currency"/"Tonnage Reference") | PD8: Cargo Tarrif Graduations (tonnes per Tonnage Reference) (1,000,000 used at end as catch all) | PM8: Cargo Tarrifs ("Currency"/"Tonnage Reference") | PW8: Days delay | PY8: Amount per Capacity Tarrif Graduations | QI8: Amounts per Cargo Tarrif Graduations | QT8: Round trip distance Main fuel | QU8: Round Trip Distance on Auxiliary fuel | QV8: Vessel Loading rate | QW8: Vessel Un-Loading rate | QX8: Vessel Speed | QY8: Main Engine Fuel burn rate | QZ8: MDO / MGO burn rate | RA8: Days at Avg Speed Main Fuel | RB8: Days at Avg Speed Auxiliary Fuel | RC8: Days Loading | RD8: Days unloading | RE8: Extra Days due to Canal use | RF8: Lay days allowance (50% each port) | RG8: Main Fuel HFO / VLSFO Fuel Price | RH8: Auxiliary Fuel (MDO / MGO / LNG) Price | RI8: Main Fuel Cost | RJ8: Auxiliary Fuel Cost | RK8: FX rate per USD | RL8: Fixed fee | RM8: Berthing Charge | RN8: Anchorage Charge | RO8: Per T_Cargo (wet) Charge | RP8: RMB/T_Cargo (wet)/day berthed | RQ8: RMB/T_Cargo (wet)/day anchored | RR8: RMB/NRT | RS8: RMB/NRT/day berthed | RT8: RMB/NRT/day anchored | RU8: RMB/GRT | RV8: RMB/GRT/day berthed | RW8: RMB/GRT/day anchored | RX8: RMB/LOA | RY8: RMB/LOA/day berthed | RZ8: RMB/LOA/day anchored | SA8: Time Charter Rate | SB8: Time Charter Cost | SC8: Canal Costs | SD8: Total Cost for Leg - before Insurance & Commission | SE8: Total Cost for Leg - with Insurance & Commission | SF8: Per tonne cargo incl. Insurance & Commission | SH8: Vessel dwt | SI8: Vessel Class for timecharter & fuel burn rates | SJ8: Vessel Class for distance, canals, loading and unloading rates, fuel prices | SK8: Estimated LOA (length over all) (m) | SL8: Estimated NRT (net register tons) | SM8: Estimated GRT (gross register tons) | SO8: Handysize | SP8: Supramax loading rates | SQ8: Panamax loading rates | SR8: NeoPanamax loading rate | SS8: Suezmax loading rate | ST8: Capesize loading rates | SU8: VLOC loading rates | SW8: Distance using Main Engine Fuel | SX8: Distance using Auxiliary Fuel | SY8: Applicable Time Charter Index | SZ8: Applicable Fuel Region | TA8: Main Engine Fuel | TB8: Auxiliary Fuel | TC8: Canals used | TD8: Distance using Main Engine Fuel | TE8: Distance using Auxiliary Fuel | TF8: Applicable Time Charter Index | TG8: Applicable Fuel Region | TH8: Main Engine Fuel | TI8: Auxiliary Fuel | TJ8: Canals used | TK8: Distance using Main Engine Fuel | TL8: Distance using Auxiliary Fuel | TM8: Applicable Time Charter Index | TN8: Applicable Fuel Region | TO8: Main Engine Fuel | TP8: Auxiliary Fuel | TQ8: Canals used | TR8: Distance using Main Engine Fuel | TS8: Distance using Auxiliary Fuel | TT8: Applicable Time Charter Index | TU8: Applicable Fuel Region | TV8: Main Engine Fuel | TW8: Auxiliary Fuel | TX8: Canals used | TY8: Distance using Main Engine Fuel | TZ8: Distance using Auxiliary Fuel | UA8: Applicable Time Charter Index | UB8: Applicable Fuel Region | UC8: Main Engine Fuel | UD8: Auxiliary Fuel | UE8: Canals used | UF8: Distance using Main Engine Fuel | UG8: Distance using Auxiliary Fuel | UH8: Applicable Time Charter Index | UI8: Applicable Fuel Region | UJ8: Main Engine Fuel | UK8: Auxiliary Fuel | UL8: Canals used | UM8: Distance using Main Engine Fuel | UN8: Distance using Auxiliary Fuel | UO8: Applicable Time Charter Index | UP8: Applicable Fuel Region | UQ8: Main Engine Fuel | UR8: Auxiliary Fuel | US8: Canals used | UU8: HSFO (180 / 380) | UV8: VLSFO | UW8: LNG | UX8: MDO/MGO Regular | UY8: MDO/MGO Low Sulphur | VA8: Unloading rate Handysize | VB8: Unloading rate Supramax | VC8: Unloading rate Panamax | VD8: Unloading rate NeoPanamax | VE8: Unloading rate Suezmax | VF8: Unloading rate Capesize | VG8: Unloading rate VLOC | VH8: Currency | VI8: Fixed fee | VJ8: RMB per day berthed | VK8: RMB per day anchored | VL8: RMB/T_Cargo (wet) | VM8: RMB/T_Cargo (wet)/day berthed | VN8: RMB/T_Cargo (wet)/day anchored | VO8: RMB/NRT | VP8: RMB/NRT/day berthed | VQ8: RMB/NRT/day anchored | VR8: RMB/GRT | VS8: RMB/GRT/day berthed | VT8: RMB/GRT/day anchored | VU8: RMB/LOA | VV8: RMB/LOA/day berthed | VW8: RMB/LOA/day anchored | VY8: Canal | VZ8: Currency | WA8: Capacity Tarrif Graduations (avg of laden and ballast) (tonnes per Tonnage Reference) (1,000,000 used at end as catch all) | WK8: Capacity Tarrifs (avg of laden and ballast) ("Currency"/"Tonnage Reference") | WU8: Cargo Tarrif Graduations (tonnes per Tonnage Reference) (1,000,000 used at end as catch all) | XD8: Cargo Tarrifs ("Currency"/"Tonnage Reference") | XN8: Days delay | XP8: Amount per Capacity Tarrif Graduations | XZ8: Amounts per Cargo Tarrif Graduations | YK8: Round trip distance Main fuel | YL8: Round Trip Distance on Auxiliary fuel | YM8: Vessel Loading rate | YN8: Vessel Un-Loading rate | YO8: Vessel Speed | YP8: Main Engine Fuel burn rate | YQ8: MDO / MGO burn rate | YR8: Days at Avg Speed Main Fuel | YS8: Days at Avg Speed Auxiliary Fuel | YT8: Days Loading | YU8: Days unloading | YV8: Extra Days due to Canal use | YW8: Lay days allowance (50% each port) | YX8: Main Fuel HFO / VLSFO Fuel Price | YY8: Auxiliary Fuel (MDO / MGO / LNG) Price | YZ8: Main Fuel Cost | ZA8: Auxiliary Fuel Cost | ZB8: FX rate per USD | ZC8: Fixed fee | ZD8: Berthing Charge | ZE8: Anchorage Charge | ZF8: Per T_Cargo (wet) Charge | ZG8: RMB/T_Cargo (wet)/day berthed | ZH8: RMB/T_Cargo (wet)/day anchored | ZI8: RMB/NRT | ZJ8: RMB/NRT/day berthed | ZK8: RMB/NRT/day anchored | ZL8: RMB/GRT | ZM8: RMB/GRT/day berthed | ZN8: RMB/GRT/day anchored | ZO8: RMB/LOA | ZP8: RMB/LOA/day berthed | ZQ8: RMB/LOA/day anchored | ZR8: Time Charter Rate | ZS8: Time Charter Cost | ZT8: Canal Costs | ZU8: Total Cost for Leg - before Insurance & Commission | ZV8: Total Cost for Leg - with Insurance & Commission | ZW8: Per tonne cargo incl. Insurance & Commission | ZY8: * | AAA8: Vessel dwt | AAB8: Vessel Class for timecharter & fuel burn rates | AAC8: Vessel Class for distance, canals, loading and unloading rates, fuel prices | AAD8: Estimated LOA (length over all) (m) | AAE8: Estimated NRT (net register tons) | AAF8: Estimated GRT (gross register tons) | AAH8: Handysize | AAI8: Supramax loading rates | AAJ8: Panamax loading rates | AAK8: NeoPanamax loading rate | AAL8: Suezmax loading rate | AAM8: Capesize loading rates | AAN8: VLOC loading rates | AAP8: Distance using Main Engine Fuel | AAQ8: Distance using Auxiliary Fuel | AAR8: Applicable Time Charter Index | AAS8: Applicable Fuel Region | AAT8: Main Engine Fuel | AAU8: Auxiliary Fuel | AAV8: Canals used | AAW8: Distance using Main Engine Fuel | AAX8: Distance using Auxiliary Fuel | AAY8: Applicable Time Charter Index | AAZ8: Applicable Fuel Region | ABA8: Main Engine Fuel | ABB8: Auxiliary Fuel | ABC8: Canals used | ABD8: Distance using Main Engine Fuel | ABE8: Distance using Auxiliary Fuel | ABF8: Applicable Time Charter Index | ABG8: Applicable Fuel Region | ABH8: Main Engine Fuel | ABI8: Auxiliary Fuel | ABJ8: Canals used | ABK8: Distance using Main Engine Fuel | ABL8: Distance using Auxiliary Fuel | ABM8: Applicable Time Charter Index | ABN8: Applicable Fuel Region | ABO8: Main Engine Fuel | ABP8: Auxiliary Fuel | ABQ8: Canals used | ABR8: Distance using Main Engine Fuel | ABS8: Distance using Auxiliary Fuel | ABT8: Applicable Time Charter Index | ABU8: Applicable Fuel Region | ABV8: Main Engine Fuel | ABW8: Auxiliary Fuel | ABX8: Canals used | ABY8: Distance using Main Engine Fuel | ABZ8: Distance using Auxiliary Fuel | ACA8: Applicable Time Charter Index | ACB8: Applicable Fuel Region | ACC8: Main Engine Fuel | ACD8: Auxiliary Fuel | ACE8: Canals used | ACF8: Distance using Main Engine Fuel | ACG8: Distance using Auxiliary Fuel | ACH8: Applicable Time Charter Index | ACI8: Applicable Fuel Region | ACJ8: Main Engine Fuel | ACK8: Auxiliary Fuel | ACL8: Canals used | ACN8: HSFO (180 / 380) | ACO8: VLSFO | ACP8: LNG | ACQ8: MDO/MGO Regular | ACR8: MDO/MGO Low Sulphur | ACT8: Unloading rate Handysize | ACU8: Unloading rate Supramax | ACV8: Unloading rate Panamax | ACW8: Unloading rate NeoPanamax | ACX8: Unloading rate Suezmax | ACY8: Unloading rate Capesize | ACZ8: Unloading rate VLOC | ADA8: Currency | ADB8: Fixed fee | ADC8: RMB per day berthed | ADD8: RMB per day anchored | ADE8: RMB/T_Cargo (wet) | ADF8: RMB/T_Cargo (wet)/day berthed | ADG8: RMB/T_Cargo (wet)/day anchored | ADH8: RMB/NRT | ADI8: RMB/NRT/day berthed | ADJ8: RMB/NRT/day anchored | ADK8: RMB/GRT | ADL8: RMB/GRT/day berthed | ADM8: RMB/GRT/day anchored | ADN8: RMB/LOA | ADO8: RMB/LOA/day berthed | ADP8: RMB/LOA/day anchored | ADR8: Canal | ADS8: Currency | ADT8: Capacity Tarrif Graduations (avg of laden and ballast) (tonnes per Tonnage Reference) (1,000,000 used at end as catch all) | AED8: Capacity Tarrifs (avg of laden and ballast) ("Currency"/"Tonnage Reference") | AEN8: Cargo Tarrif Graduations (tonnes per Tonnage Reference) (1,000,000 used at end as catch all) | AEW8: Cargo Tarrifs ("Currency"/"Tonnage Reference") | AFG8: Days delay | AFI8: Amount per Capacity Tarrif Graduations | AFS8: Amounts per Cargo Tarrif Graduations | AGD8: Round trip distance Main fuel | AGE8: Round Trip Distance on Auxiliary fuel | AGF8: Vessel Loading rate | AGG8: Vessel Un-Loading rate | AGH8: Vessel Speed | AGI8: Main Engine Fuel burn rate | AGJ8: MDO / MGO burn rate | AGK8: Days at Avg Speed Main Fuel | AGL8: Days at Avg Speed Auxiliary Fuel | AGM8: Days Loading | AGN8: Days unloading | AGO8: Extra Days due to Canal use | AGP8: Lay days allowance (50% each port) | AGQ8: Main Fuel HFO / VLSFO Fuel Price | AGR8: Auxiliary Fuel (MDO / MGO / LNG) Price | AGS8: Main Fuel Cost | AGT8: Auxiliary Fuel Cost | AGU8: FX rate per USD | AGV8: Fixed fee | AGW8: Berthing Charge | AGX8: Anchorage Charge | AGY8: Per T_Cargo (wet) Charge | AGZ8: RMB/T_Cargo (wet)/day berthed | AHA8: RMB/T_Cargo (wet)/day anchored | AHB8: RMB/NRT | AHC8: RMB/NRT/day berthed | AHD8: RMB/NRT/day anchored | AHE8: RMB/GRT | AHF8: RMB/GRT/day berthed | AHG8: RMB/GRT/day anchored | AHH8: RMB/LOA | AHI8: RMB/LOA/day berthed | AHJ8: RMB/LOA/day anchored | AHK8: Time Charter Rate | AHL8: Time Charter Cost | AHM8: Canal Costs | AHN8: Total Cost for Leg - before Insurance & Commission | AHO8: Total Cost for Leg - with Insurance & Commission | AHP8: Per tonne cargo incl. Insurance & Commission | AHR8: Vessel dwt | AHS8: Vessel Class for timecharter & fuel burn rates | AHT8: Vessel Class for distance, canals, loading and unloading rates, fuel prices | AHU8: Estimated LOA (length over all) (m) | AHV8: Estimated NRT (net register tons) | AHW8: Estimated GRT (gross register tons) | AHY8: Handysize | AHZ8: Supramax loading rates | AIA8: Panamax loading rates | AIB8: NeoPanamax loading rate | AIC8: Suezmax loading rate | AID8: Capesize loading rates | AIE8: VLOC loading rates | AIG8: Distance using Main Engine Fuel | AIH8: Distance using Auxiliary Fuel | AII8: Applicable Time Charter Index | AIJ8: Applicable Fuel Region | AIK8: Main Engine Fuel | AIL8: Auxiliary Fuel | AIM8: Canals used | AIN8: Distance using Main Engine Fuel | AIO8: Distance using Auxiliary Fuel | AIP8: Applicable Time Charter Index | AIQ8: Applicable Fuel Region | AIR8: Main Engine Fuel | AIS8: Auxiliary Fuel | AIT8: Canals used | AIU8: Distance using Main Engine Fuel | AIV8: Distance using Auxiliary Fuel | AIW8: Applicable Time Charter Index | AIX8: Applicable Fuel Region | AIY8: Main Engine Fuel | AIZ8: Auxiliary Fuel | AJA8: Canals used | AJB8: Distance using Main Engine Fuel | AJC8: Distance using Auxiliary Fuel | AJD8: Applicable Time Charter Index | AJE8: Applicable Fuel Region | AJF8: Main Engine Fuel | AJG8: Auxiliary Fuel | AJH8: Canals used | AJI8: Distance using Main Engine Fuel | AJJ8: Distance using Auxiliary Fuel | AJK8: Applicable Time Charter Index | AJL8: Applicable Fuel Region | AJM8: Main Engine Fuel | AJN8: Auxiliary Fuel | AJO8: Canals used | AJP8: Distance using Main Engine Fuel | AJQ8: Distance using Auxiliary Fuel | AJR8: Applicable Time Charter Index | AJS8: Applicable Fuel Region | AJT8: Main Engine Fuel | AJU8: Auxiliary Fuel | AJV8: Canals used | AJW8: Distance using Main Engine Fuel | AJX8: Distance using Auxiliary Fuel | AJY8: Applicable Time Charter Index | AJZ8: Applicable Fuel Region | AKA8: Main Engine Fuel | AKB8: Auxiliary Fuel | AKC8: Canals used | AKE8: HSFO (180 / 380) | AKF8: VLSFO | AKG8: LNG | AKH8: MDO/MGO Regular | AKI8: MDO/MGO Low Sulphur | AKK8: Unloading rate Handysize | AKL8: Unloading rate Supramax | AKM8: Unloading rate Panamax | AKN8: Unloading rate NeoPanamax | AKO8: Unloading rate Suezmax | AKP8: Unloading rate Capesize | AKQ8: Unloading rate VLOC | AKR8: Currency | AKS8: Fixed fee | AKT8: RMB per day berthed | AKU8: RMB per day anchored | AKV8: RMB/T_Cargo (wet) | AKW8: RMB/T_Cargo (wet)/day berthed | AKX8: RMB/T_Cargo (wet)/day anchored | AKY8: RMB/NRT | AKZ8: RMB/NRT/day berthed | ALA8: RMB/NRT/day anchored | ALB8: RMB/GRT | ALC8: RMB/GRT/day berthed | ALD8: RMB/GRT/day anchored | ALE8: RMB/LOA | ALF8: RMB/LOA/day berthed | ALG8: RMB/LOA/day anchored | ALI8: Canal | ALJ8: Currency | ALK8: Capacity Tarrif Graduations (avg of laden and ballast) (tonnes per Tonnage Reference) (1,000,000 used at end as catch all) | ALU8: Capacity Tarrifs (avg of laden and ballast) ("Currency"/"Tonnage Reference") | AME8: Cargo Tarrif Graduations (tonnes per Tonnage Reference) (1,000,000 used at end as catch all) | AMN8: Cargo Tarrifs ("Currency"/"Tonnage Reference") | AMX8: Days delay | AMZ8: Amount per Capacity Tarrif Graduations | ANJ8: Amounts per Cargo Tarrif Graduations | ANU8: Round trip distance Main fuel | ANV8: Round Trip Distance on Auxiliary fuel | ANW8: Vessel Loading rate | ANX8: Vessel Un-Loading rate | ANY8: Vessel Speed | ANZ8: Main Engine Fuel burn rate | AOA8: MDO / MGO burn rate | AOB8: Days at Avg Speed Main Fuel | AOC8: Days at Avg Speed Auxiliary Fuel | AOD8: Days Loading | AOE8: Days unloading | AOF8: Extra Days due to Canal use | AOG8: Lay days allowance (50% each port) | AOH8: Main Fuel HFO / VLSFO Fuel Price | AOI8: Auxiliary Fuel (MDO / MGO / LNG) Price | AOJ8: Main Fuel Cost | AOK8: Auxiliary Fuel Cost | AOL8: FX rate per USD | AOM8: Fixed fee | AON8: Berthing Charge | AOO8: Anchorage Charge | AOP8: Per T_Cargo (wet) Charge | AOQ8: RMB/T_Cargo (wet)/day berthed | AOR8: RMB/T_Cargo (wet)/day anchored | AOS8: RMB/NRT | AOT8: RMB/NRT/day berthed | AOU8: RMB/NRT/day anchored | AOV8: RMB/GRT | AOW8: RMB/GRT/day berthed | AOX8: RMB/GRT/day anchored | AOY8: RMB/LOA | AOZ8: RMB/LOA/day berthed | APA8: RMB/LOA/day anchored | APB8: Time Charter Rate | APC8: Time Charter Cost | APD8: Canal Costs | APE8: Total Cost for Leg - before Insurance & Commission | APF8: Total Cost for Leg - with Insurance & Commission | APG8: Per tonne cargo incl. Insurance & Commission | API8: * | APK8: Qingdao Freight | APL8: Actual Port Freight | APM8: Freight Differential | APO8: *
C9: date data received | D9: e.g. whomever | E9: e.g. Bel Air, Weipa, CBG, Bauxite Hills etc | F9: US$/t | G9: - | H9: - | I9: % | J9: % | K9: % | L9: % | M9: % | N9: % | O9: % | P9: tonnes (on same basis as price (wmt/dmt)) | Q9: - | R9: - | T9: * | W9: % | X9: % | Y9: % | Z9: % | AA9: % | AB9: % | AC9: % | AE9: e.g. Bel Air, Weipa, CBG, Bauxite Hills etc | AF9: % | AG9: % | AH9: % | AI9: % | AJ9: % | AK9: % | AL9: % | AM9: LT, HT-B, HT-D | AN9: dmt | AO9: Yes / No | AP9: - | AQ9: second port (transloading) | AR9: dmt (should be total cargo / whole number to ~50,000t increments) | AS9: - | AT9: Guinea 45/3 LT, Australia HT, Indonesia LT | AU9: CBIX LT, CBIX HT | AV9: - | AW9: - | AX9: US$/dmt | AY9: US$/dmt incl. Insurance | AZ9: US$/dmt CIF | BA9: US$/dmt_Bx CIF | BC9: - | BD9: US$/dmt CIF | BE9: US$/dmt CIF | BF9: US$/dmt CIF | BG9: US$/dmt CIF | BH9: US$/dmt CIF | BI9: US$/dmt CIF | BK9: * | BM9: US$/dmt CIF | BN9: % | BO9: % | BP9: % | BQ9: % | BR9: % | BS9: % | BT9: % | BU9: LT, HT-B, HT-D | BV9: US$/dmt_Bx landed China | BX9: % | BY9: - | BZ9: - | CA9: - | CB9: GJ/t | CC9: % | CD9: % | CE9: - | CG9: % | CH9: % | CI9: % | CJ9: dmt Bx / dmt AA | CK9: US$/t AA | CL9: t.NAOH / t.AA | CM9: US$/t AA | CN9: US$/t AA | CO9: US$/t AA | CP9: dmt_mud / t.AA | CQ9: US$/t AA | CR9: US$/t AA | CT9: * | CV9: US$/dmt CIF | CW9: % | CX9: % | CY9: % | CZ9: % | DA9: % | DB9: % | DC9: % | DD9: LT, HT-B, HT-D | DE9: US$/dmt_Bx landed China | DG9: % | DH9: - | DI9: - | DJ9: - | DK9: GJ/t | DL9: % | DM9: % | DN9: - | DP9: % | DQ9: % | DR9: % | DS9: dmt Bx / dmt AA | DT9: US$/t AA | DU9: t.NAOH / t.AA | DV9: US$/t AA | DW9: US$/t AA | DX9: US$/t AA | DY9: dmt_mud / t.AA | DZ9: US$/t AA | EA9: US$/t AA | EC9: * | EE9: US$/dmt CIF | EF9: % | EG9: % | EH9: % | EI9: % | EJ9: % | EK9: % | EL9: % | EM9: LT, HT-B, HT-D | EN9: US$/dmt_Bx landed China | EP9: % | EQ9: - | ER9: - | ES9: - | ET9: GJ/t | EU9: % | EV9: % | EW9: - | EY9: % | EZ9: % | FA9: % | FB9: dmt Bx / dmt AA | FC9: US$/t AA | FD9: t.NAOH / t.AA | FE9: US$/t AA | FF9: US$/t AA | FG9: US$/t AA | FH9: dmt_mud / t.AA | FI9: US$/t AA | FJ9: US$/t AA | FL9: * | FN9: US$/dmt CIF | FO9: % | FP9: % | FQ9: % | FR9: % | FS9: % | FT9: % | FU9: % | FV9: LT, HT-B, HT-D | FW9: US$/dmt_Bx landed China | FY9: % | FZ9: - | GA9: - | GB9: - | GC9: GJ/t | GD9: % | GE9: % | GF9: - | GH9: % | GI9: % | GJ9: % | GK9: dmt Bx / dmt AA | GL9: US$/t AA | GM9: t.NAOH / t.AA | GN9: US$/t AA | GO9: US$/t AA | GP9: US$/t AA | GQ9: dmt_mud / t.AA | GR9: US$/t AA | GS9: US$/t AA | GU9: US$/dmt CIF | GV9: % | GW9: % | GX9: % | GY9: % | GZ9: % | HA9: % | HB9: % | HC9: LT, HT-B, HT-D | HD9: US$/dmt_Bx landed China | HF9: % | HG9: - | HH9: - | HI9: - | HJ9: GJ/t | HK9: % | HL9: % | HM9: - | HO9: % | HP9: % | HQ9: % | HR9: dmt Bx / dmt AA | HS9: US$/t AA | HT9: t.NAOH / t.AA | HU9: US$/t AA | HV9: US$/t AA | HW9: US$/t AA | HX9: dmt_mud / t.AA | HY9: US$/t AA | HZ9: US$/t AA | IB9: * | ID9: - | IF9: % | IG9: % | IH9: % | II9: % | IJ9: % | IK9: % | IL9: % | IM9: HT-D, HT-B, LT | IN9: US$/dmt_Bx landed China | IO9: dwt | IP9: name | IQ9: index name | IR9: index name | IT9: * | IV9: US$/GJ | IW9: US$/t pure NaOH | IX9: US$/t Lime | IY9: US$/dmt mud | JA9: - | JB9: - | JC9: - | JD9: - | JF9: - | JG9: - | JH9: - | JI9: - | JJ9: % | JK9: - | JL9: - | JM9: - | JN9: % | JO9: - | JP9: - | JQ9: - | JR9: - | JS9: - | JT9: - | JU9: days | JV9: % | JW9: % | JX9: days | JY9: - | JZ9: - | KA9: - | KB9: - | KC9: - | KD9: - | KE9: - | KF9: - | KG9: - | KH9: - | KI9: - | KJ9: - | KK9: - | KL9: - | KM9: % | KO9: * | KQ9: tonnes | KR9: Panamax, Cape etc | KS9: Panamax, Cape etc | KT9: (m) | KU9: net register tons | KV9: gross register tons | KX9: wmt/day | KY9: wmt/day | KZ9: wmt/day | LA9: wmt/day | LB9: wmt/day | LC9: wmt/day | LD9: wmt/day | LF9: knots 1-way | LG9: knots 1-way | LH9: name | LI9: name | LJ9: name | LK9: name | LL9: name | LM9: knots 1-way | LN9: knots 1-way | LO9: name | LP9: name | LQ9: name | LR9: name | LS9: name | LT9: knots 1-way | LU9: knots 1-way | LV9: name | LW9: name | LX9: name | LY9: name | LZ9: name | MA9: knots 1-way | MB9: knots 1-way | MC9: name | MD9: name | ME9: name | MF9: name | MG9: name | MH9: knots 1-way | MI9: knots 1-way | MJ9: name | MK9: name | ML9: name | MM9: name | MN9: name | MO9: knots 1-way | MP9: knots 1-way | MQ9: name | MR9: name | MS9: name | MT9: name | MU9: name | MV9: knots 1-way | MW9: knots 1-way | MX9: name | MY9: name | MZ9: name | NA9: name | NB9: name | ND9: US$/t | NE9: US$/t | NF9: US$/t | NG9: US$/t | NH9: US$/t | NJ9: tpd | NK9: tpd | NL9: tpd | NM9: tpd | NN9: tpd | NO9: tpd | NP9: tpd | NQ9: name | NR9: Currency | NS9: Currency | NT9: Currency | NU9: Currency | NV9: Currency | NW9: Currency | NX9: Currency | NY9: Currency | NZ9: Currency | OA9: Currency | OB9: Currency | OC9: Currency | OD9: Currency | OE9: Currency | OF9: Currency | OH9: name | OI9: code | OJ9: Tonnage Reference | OK9: 1st | OL9: Next | OM9: Next | ON9: Next | OO9: Next | OP9: Next | OQ9: Next | OR9: Next | OS9: Next | OT9: 1st | OU9: Next | OV9: Next | OW9: Next | OX9: Next | OY9: Next | OZ9: Next | PA9: Next | PB9: Next | PC9: rem | PD9: 1st | PE9: Next | PF9: Next | PG9: Next | PH9: Next | PI9: Next | PJ9: Next | PK9: Next | PL9: Next | PM9: 1st | PN9: Next | PO9: Next | PP9: Next | PQ9: Next | PR9: Next | PS9: Next | PT9: Next | PU9: Next | PV9: rem | PW9: days each way | PY9: Tonnage Reference | PZ9: 1st | QA9: Next | QB9: Next | QC9: Next | QD9: Next | QE9: Next | QF9: Next | QG9: Next | QH9: Next | QI9: Tonnage Reference | QJ9: 1st | QK9: Next | QL9: Next | QM9: Next | QN9: Next | QO9: Next | QP9: Next | QQ9: Next | QR9: Next | QT9: kn | QU9: kn | QV9: tpd | QW9: tpd | QX9: kn | QY9: tpd | QZ9: tpd | RA9: days | RB9: days | RC9: days | RD9: days | RE9: days | RF9: days | RG9: US$/t | RH9: US$/t | RI9: US$ | RJ9: US$ | RL9: US$ | RM9: US$ | RN9: US$ | RO9: US$ | RP9: US$ | RQ9: US$ | RR9: US$ | RS9: US$ | RT9: US$ | RU9: US$ | RV9: US$ | RW9: US$ | RX9: US$ | RY9: US$ | RZ9: US$ | SA9: US$/day | SB9: US$ | SC9: US$ | SD9: US$ | SE9: US$ | SF9: US$/dmt | SH9: tonnes | SI9: Panamax, Cape etc | SJ9: Panamax, Cape etc | SK9: (m) | SL9: net register tons | SM9: gross register tons | SO9: wmt/day | SP9: wmt/day | SQ9: wmt/day | SR9: wmt/day | SS9: wmt/day | ST9: wmt/day | SU9: wmt/day | SW9: knots 1-way | SX9: knots 1-way | SY9: name | SZ9: name | TA9: name | TB9: name | TC9: name | TD9: knots 1-way | TE9: knots 1-way | TF9: name | TG9: name | TH9: name | TI9: name | TJ9: name | TK9: knots 1-way | TL9: knots 1-way | TM9: name | TN9: name | TO9: name | TP9: name | TQ9: name | TR9: knots 1-way | TS9: knots 1-way | TT9: name | TU9: name | TV9: name | TW9: name | TX9: name | TY9: knots 1-way | TZ9: knots 1-way | UA9: name | UB9: name | UC9: name | UD9: name | UE9: name | UF9: knots 1-way | UG9: knots 1-way | UH9: name | UI9: name | UJ9: name | UK9: name | UL9: name | UM9: knots 1-way | UN9: knots 1-way | UO9: name | UP9: name | UQ9: name | UR9: name | US9: name | UU9: US$/t | UV9: US$/t | UW9: US$/t | UX9: US$/t | UY9: US$/t | VA9: tpd | VB9: tpd | VC9: tpd | VD9: tpd | VE9: tpd | VF9: tpd | VG9: tpd | VH9: name | VI9: Currency | VJ9: Currency | VK9: Currency | VL9: Currency | VM9: Currency | VN9: Currency | VO9: Currency | VP9: Currency | VQ9: Currency | VR9: Currency | VS9: Currency | VT9: Currency | VU9: Currency | VV9: Currency | VW9: Currency | VY9: name | VZ9: code | WA9: Tonnage Reference | WB9: 1st | WC9: Next | WD9: Next | WE9: Next | WF9: Next | WG9: Next | WH9: Next | WI9: Next | WJ9: Next | WK9: 1st | WL9: Next | WM9: Next | WN9: Next | WO9: Next | WP9: Next | WQ9: Next | WR9: Next | WS9: Next | WT9: rem | WU9: 1st | WV9: Next | WW9: Next | WX9: Next | WY9: Next | WZ9: Next | XA9: Next | XB9: Next | XC9: Next | XD9: 1st | XE9: Next | XF9: Next | XG9: Next | XH9: Next | XI9: Next | XJ9: Next | XK9: Next | XL9: Next | XM9: rem | XN9: days each way | XP9: Tonnage Reference | XQ9: 1st | XR9: Next | XS9: Next | XT9: Next | XU9: Next | XV9: Next | XW9: Next | XX9: Next | XY9: Next | XZ9: Tonnage Reference | YA9: 1st | YB9: Next | YC9: Next | YD9: Next | YE9: Next | YF9: Next | YG9: Next | YH9: Next | YI9: Next | YK9: kn | YL9: kn | YM9: tpd | YN9: tpd | YO9: kn | YP9: tpd | YQ9: tpd | YR9: days | YS9: days | YT9: days | YU9: days | YV9: days | YW9: days | YX9: US$/t | YY9: US$/t | YZ9: US$ | ZA9: US$ | ZC9: US$ | ZD9: US$ | ZE9: US$ | ZF9: US$ | ZG9: US$ | ZH9: US$ | ZI9: US$ | ZJ9: US$ | ZK9: US$ | ZL9: US$ | ZM9: US$ | ZN9: US$ | ZO9: US$ | ZP9: US$ | ZQ9: US$ | ZR9: US$/day | ZS9: US$ | ZT9: US$ | ZU9: US$ | ZV9: US$ | ZW9: US$/dmt | ZY9: * | AAA9: tonnes | AAB9: Panamax, Cape etc | AAC9: Panamax, Cape etc | AAD9: (m) | AAE9: net register tons | AAF9: gross register tons | AAH9: wmt/day | AAI9: wmt/day | AAJ9: wmt/day | AAK9: wmt/day | AAL9: wmt/day | AAM9: wmt/day | AAN9: wmt/day | AAP9: knots 1-way | AAQ9: knots 1-way | AAR9: name | AAS9: name | AAT9: name | AAU9: name | AAV9: name | AAW9: knots 1-way | AAX9: knots 1-way | AAY9: name | AAZ9: name | ABA9: name | ABB9: name | ABC9: name | ABD9: knots 1-way | ABE9: knots 1-way | ABF9: name | ABG9: name | ABH9: name | ABI9: name | ABJ9: name | ABK9: knots 1-way | ABL9: knots 1-way | ABM9: name | ABN9: name | ABO9: name | ABP9: name | ABQ9: name | ABR9: knots 1-way | ABS9: knots 1-way | ABT9: name | ABU9: name | ABV9: name | ABW9: name | ABX9: name | ABY9: knots 1-way | ABZ9: knots 1-way | ACA9: name | ACB9: name | ACC9: name | ACD9: name | ACE9: name | ACF9: knots 1-way | ACG9: knots 1-way | ACH9: name | ACI9: name | ACJ9: name | ACK9: name | ACL9: name | ACN9: US$/t | ACO9: US$/t | ACP9: US$/t | ACQ9: US$/t | ACR9: US$/t | ACT9: tpd | ACU9: tpd | ACV9: tpd | ACW9: tpd | ACX9: tpd | ACY9: tpd | ACZ9: tpd | ADA9: name | ADB9: Currency | ADC9: Currency | ADD9: Currency | ADE9: Currency | ADF9: Currency | ADG9: Currency | ADH9: Currency | ADI9: Currency | ADJ9: Currency | ADK9: Currency | ADL9: Currency | ADM9: Currency | ADN9: Currency | ADO9: Currency | ADP9: Currency | ADR9: name | ADS9: code | ADT9: Tonnage Reference | ADU9: 1st | ADV9: Next | ADW9: Next | ADX9: Next | ADY9: Next | ADZ9: Next | AEA9: Next | AEB9: Next | AEC9: Next | AED9: 1st | AEE9: Next | AEF9: Next | AEG9: Next | AEH9: Next | AEI9: Next | AEJ9: Next | AEK9: Next | AEL9: Next | AEM9: rem | AEN9: 1st | AEO9: Next | AEP9: Next | AEQ9: Next | AER9: Next | AES9: Next | AET9: Next | AEU9: Next | AEV9: Next | AEW9: 1st | AEX9: Next | AEY9: Next | AEZ9: Next | AFA9: Next | AFB9: Next | AFC9: Next | AFD9: Next | AFE9: Next | AFF9: rem | AFG9: days each way | AFI9: Tonnage Reference | AFJ9: 1st | AFK9: Next | AFL9: Next | AFM9: Next | AFN9: Next | AFO9: Next | AFP9: Next | AFQ9: Next | AFR9: Next | AFS9: Tonnage Reference | AFT9: 1st | AFU9: Next | AFV9: Next | AFW9: Next | AFX9: Next | AFY9: Next | AFZ9: Next | AGA9: Next | AGB9: Next | AGD9: kn | AGE9: kn | AGF9: tpd | AGG9: tpd | AGH9: kn | AGI9: tpd | AGJ9: tpd | AGK9: days | AGL9: days | AGM9: days | AGN9: days | AGO9: days | AGP9: days | AGQ9: US$/t | AGR9: US$/t | AGS9: US$ | AGT9: US$ | AGV9: US$ | AGW9: US$ | AGX9: US$ | AGY9: US$ | AGZ9: US$ | AHA9: US$ | AHB9: US$ | AHC9: US$ | AHD9: US$ | AHE9: US$ | AHF9: US$ | AHG9: US$ | AHH9: US$ | AHI9: US$ | AHJ9: US$ | AHK9: US$/day | AHL9: US$ | AHM9: US$ | AHN9: US$ | AHO9: US$ | AHP9: US$/dmt | AHR9: tonnes | AHS9: Panamax, Cape etc | AHT9: Panamax, Cape etc | AHU9: (m) | AHV9: net register tons | AHW9: gross register tons | AHY9: wmt/day | AHZ9: wmt/day | AIA9: wmt/day | AIB9: wmt/day | AIC9: wmt/day | AID9: wmt/day | AIE9: wmt/day | AIG9: knots 1-way | AIH9: knots 1-way | AII9: name | AIJ9: name | AIK9: name | AIL9: name | AIM9: name | AIN9: knots 1-way | AIO9: knots 1-way | AIP9: name | AIQ9: name | AIR9: name | AIS9: name | AIT9: name | AIU9: knots 1-way | AIV9: knots 1-way | AIW9: name | AIX9: name | AIY9: name | AIZ9: name | AJA9: name | AJB9: knots 1-way | AJC9: knots 1-way | AJD9: name | AJE9: name | AJF9: name | AJG9: name | AJH9: name | AJI9: knots 1-way | AJJ9: knots 1-way | AJK9: name | AJL9: name | AJM9: name | AJN9: name | AJO9: name | AJP9: knots 1-way | AJQ9: knots 1-way | AJR9: name | AJS9: name | AJT9: name | AJU9: name | AJV9: name | AJW9: knots 1-way | AJX9: knots 1-way | AJY9: name | AJZ9: name | AKA9: name | AKB9: name | AKC9: name | AKE9: US$/t | AKF9: US$/t | AKG9: US$/t | AKH9: US$/t | AKI9: US$/t | AKK9: tpd | AKL9: tpd | AKM9: tpd | AKN9: tpd | AKO9: tpd | AKP9: tpd | AKQ9: tpd | AKR9: name | AKS9: Currency | AKT9: Currency | AKU9: Currency | AKV9: Currency | AKW9: Currency | AKX9: Currency | AKY9: Currency | AKZ9: Currency | ALA9: Currency | ALB9: Currency | ALC9: Currency | ALD9: Currency | ALE9: Currency | ALF9: Currency | ALG9: Currency | ALI9: name | ALJ9: code | ALK9: Tonnage Reference | ALL9: 1st | ALM9: Next | ALN9: Next | ALO9: Next | ALP9: Next | ALQ9: Next | ALR9: Next | ALS9: Next | ALT9: Next | ALU9: 1st | ALV9: Next | ALW9: Next | ALX9: Next | ALY9: Next | ALZ9: Next | AMA9: Next | AMB9: Next | AMC9: Next | AMD9: rem | AME9: 1st | AMF9: Next | AMG9: Next | AMH9: Next | AMI9: Next | AMJ9: Next | AMK9: Next | AML9: Next | AMM9: Next | AMN9: 1st | AMO9: Next | AMP9: Next | AMQ9: Next | AMR9: Next | AMS9: Next | AMT9: Next | AMU9: Next | AMV9: Next | AMW9: rem | AMX9: days each way | AMZ9: Tonnage Reference | ANA9: 1st | ANB9: Next | ANC9: Next | AND9: Next | ANE9: Next | ANF9: Next | ANG9: Next | ANH9: Next | ANI9: Next | ANJ9: Tonnage Reference | ANK9: 1st | ANL9: Next | ANM9: Next | ANN9: Next | ANO9: Next | ANP9: Next | ANQ9: Next | ANR9: Next | ANS9: Next | ANU9: kn | ANV9: kn | ANW9: tpd | ANX9: tpd | ANY9: kn | ANZ9: tpd | AOA9: tpd | AOB9: days | AOC9: days | AOD9: days | AOE9: days | AOF9: days | AOG9: days | AOH9: US$/t | AOI9: US$/t | AOJ9: US$ | AOK9: US$ | AOM9: US$ | AON9: US$ | AOO9: US$ | AOP9: US$ | AOQ9: US$ | AOR9: US$ | AOS9: US$ | AOT9: US$ | AOU9: US$ | AOV9: US$ | AOW9: US$ | AOX9: US$ | AOY9: US$ | AOZ9: US$ | APA9: US$ | APB9: US$/day | APC9: US$ | APD9: US$ | APE9: US$ | APF9: US$ | APG9: US$/dmt | API9: * | APK9: US$/dmt incl. Insurance | APL9: US$/dmt incl. Insurance | APM9: US$/dmt incl. Insurance | APO9: *
